odoo8_addon_delivery_carrier_label_gls-8.0.0.1.1-py3.8-nspkg.pth
odoo_addons/delivery_carrier_label_gls/README.rst
odoo_addons/delivery_carrier_label_gls/__init__.py
odoo_addons/delivery_carrier_label_gls/__openerp__.py
odoo_addons/delivery_carrier_label_gls/data/delivery_carrier.xml
odoo_addons/delivery_carrier_label_gls/data/sequence.xml
odoo_addons/delivery_carrier_label_gls/demo/company.xml
odoo_addons/delivery_carrier_label_gls/demo/config.yml
odoo_addons/delivery_carrier_label_gls/demo/product.xml
odoo_addons/delivery_carrier_label_gls/demo/stock.move.csv
odoo_addons/delivery_carrier_label_gls/demo/stock.picking.csv
odoo_addons/delivery_carrier_label_gls/doc/GLS BOX FR V04.02  26-09-2013.pdf
odoo_addons/delivery_carrier_label_gls/i18n/am.po
odoo_addons/delivery_carrier_label_gls/i18n/ar.po
odoo_addons/delivery_carrier_label_gls/i18n/bg.po
odoo_addons/delivery_carrier_label_gls/i18n/bs.po
odoo_addons/delivery_carrier_label_gls/i18n/ca.po
odoo_addons/delivery_carrier_label_gls/i18n/ca_ES.po
odoo_addons/delivery_carrier_label_gls/i18n/cs.po
odoo_addons/delivery_carrier_label_gls/i18n/da.po
odoo_addons/delivery_carrier_label_gls/i18n/de.po
odoo_addons/delivery_carrier_label_gls/i18n/delivery_carrier_label_gls.pot
odoo_addons/delivery_carrier_label_gls/i18n/el_GR.po
odoo_addons/delivery_carrier_label_gls/i18n/en_AU.po
odoo_addons/delivery_carrier_label_gls/i18n/en_GB.po
odoo_addons/delivery_carrier_label_gls/i18n/es.po
odoo_addons/delivery_carrier_label_gls/i18n/es_AR.po
odoo_addons/delivery_carrier_label_gls/i18n/es_CL.po
odoo_addons/delivery_carrier_label_gls/i18n/es_CO.po
odoo_addons/delivery_carrier_label_gls/i18n/es_CR.po
odoo_addons/delivery_carrier_label_gls/i18n/es_DO.po
odoo_addons/delivery_carrier_label_gls/i18n/es_EC.po
odoo_addons/delivery_carrier_label_gls/i18n/es_MX.po
odoo_addons/delivery_carrier_label_gls/i18n/es_PE.po
odoo_addons/delivery_carrier_label_gls/i18n/es_PY.po
odoo_addons/delivery_carrier_label_gls/i18n/es_VE.po
odoo8_addon_delivery_carrier_label_gls-8.0.0.1.1.dist-info/METADATA
odoo8_addon_delivery_carrier_label_gls-8.0.0.1.1.dist-info/WHEEL
odoo8_addon_delivery_carrier_label_gls-8.0.0.1.1.dist-info/namespace_packages.txt
odoo8_addon_delivery_carrier_label_gls-8.0.0.1.1.dist-info/top_level.txt
odoo8_addon_delivery_carrier_label_gls-8.0.0.1.1.dist-info/RECORD
